odoo/addons/mail_activity_reminder/README.rst
odoo/addons/mail_activity_reminder/__init__.py
odoo/addons/mail_activity_reminder/__manifest__.py
odoo/addons/mail_activity_reminder/data/mail_activity_reminder_cron.xml
odoo/addons/mail_activity_reminder/data/mail_activity_template.xml
odoo/addons/mail_activity_reminder/i18n/es.po
odoo/addons/mail_activity_reminder/i18n/fr.po
odoo/addons/mail_activity_reminder/i18n/it.po
odoo/addons/mail_activity_reminder/i18n/mail_activity_reminder.pot
odoo/addons/mail_activity_reminder/i18n/pt.po
odoo/addons/mail_activity_reminder/models/__init__.py
odoo/addons/mail_activity_reminder/models/mail_activity.py
odoo/addons/mail_activity_reminder/models/mail_activity_type.py
odoo/addons/mail_activity_reminder/models/mail_thread.py
odoo/addons/mail_activity_reminder/readme/CONFIGURE.md
odoo/addons/mail_activity_reminder/readme/CONTRIBUTORS.md
odoo/addons/mail_activity_reminder/readme/DESCRIPTION.md
odoo/addons/mail_activity_reminder/static/description/icon.png
odoo/addons/mail_activity_reminder/static/description/index.html
odoo/addons/mail_activity_reminder/tests/__init__.py
odoo/addons/mail_activity_reminder/tests/test_mail_activity_reminder.py
odoo/addons/mail_activity_reminder/views/mail_activity_type.xml
odoo_addon_mail_activity_reminder-18.0.1.0.0.2.dist-info/METADATA
odoo_addon_mail_activity_reminder-18.0.1.0.0.2.dist-info/WHEEL
odoo_addon_mail_activity_reminder-18.0.1.0.0.2.dist-info/top_level.txt
odoo_addon_mail_activity_reminder-18.0.1.0.0.2.dist-info/RECORD
